MANIFEST.in
README.md
requirements.txt
setup.cfg
setup.py
bin/ipxact2sv
ipxact2sv/__init__.py
ipxact2sv/ipxact2hdlCommon.py
ipxact2sv/validate.py
ipxact2sv.egg-info/PKG-INFO
ipxact2sv.egg-info/SOURCES.txt
ipxact2sv.egg-info/dependency_links.txt
ipxact2sv.egg-info/not-zip-safe
ipxact2sv.egg-info/requires.txt
ipxact2sv.egg-info/top_level.txt
ipxact2sv/xml/autoConfigure.xsd
ipxact2sv/xml/busInterface.xsd
ipxact2sv/xml/commonStructures.xsd
ipxact2sv/xml/component.xsd
ipxact2sv/xml/configurable.xsd
ipxact2sv/xml/constraints.xsd
ipxact2sv/xml/file.xsd
ipxact2sv/xml/fileType.xsd
ipxact2sv/xml/generator.xsd
ipxact2sv/xml/identifier.xsd
ipxact2sv/xml/memoryMap.xsd
ipxact2sv/xml/model.xsd
ipxact2sv/xml/port.xsd
ipxact2sv/xml/signalDrivers.xsd
ipxact2sv/xml/simpleTypes.xsd
ipxact2sv/xml/subInstances.xsd