Metadata-Version: 2.1
Name: ipxact2sv
Version: 1.1
Summary: Generate SystemVerilog, html, rst, md, pdf from an IPXACT description
Home-page: https://github.com/paulmsv/ipxact2sv
Author: paulmsv
Author-email: bobkovpg@gmail.com
License: UNKNOWN
Keywords: ipxact2sv SystemVerilog html rst md pdf IPXACT
Platform: UNKNOWN
Classifier: Development Status :: 5 - Production/Stable
Classifier: License :: OSI Approved :: GNU General Public License v2 (GPLv2)
Classifier: Programming Language :: Python :: 3
Classifier: Topic :: Text Processing :: Linguistic
Requires-Python: >=3
